rtl/core/register_file.sv
module register_file #(
    parameter int DATA_WIDTH = 64,
    parameter int ADDR_WIDTH = 8,
    parameter int REG_COUNT  = (1 << ADDR_WIDTH)
) (
    input  logic                  clk,
    input  logic                  rst,
    input  logic [ADDR_WIDTH-1:0] read_addr_a,
    output logic [DATA_WIDTH-1:0] read_data_a,
    input  logic [ADDR_WIDTH-1:0] read_addr_b,
    output logic [DATA_WIDTH-1:0] read_data_b,
    input  logic                  write_enable,
    input  logic [ADDR_WIDTH-1:0] write_addr,
    input  logic [DATA_WIDTH-1:0] write_data
);
    logic [DATA_WIDTH-1:0] registers [0:REG_COUNT-1];

    // R0 is architecturally hardwired to zero.
    assign read_data_a = (read_addr_a == '0) ? '0 : registers[read_addr_a];
    assign read_data_b = (read_addr_b == '0) ? '0 : registers[read_addr_b];

    integer i;
    always_ff @(posedge clk or posedge rst) begin
        if (rst) begin
            for (i = 0; i < REG_COUNT; i = i + 1)
                registers[i] <= '0;
        end else if (write_enable && (write_addr != '0)) begin
            registers[write_addr] <= write_data;
        end
    end
endmodule

sim/testbench/register_file_tb.sv
`timescale 1ns/1ps
module register_file_tb;
    localparam int DATA_WIDTH = 64;
    localparam int ADDR_WIDTH = 8;
    logic clk = 0;
    logic rst = 0;
    logic [ADDR_WIDTH-1:0] read_addr_a = 0, read_addr_b = 0;
    logic [DATA_WIDTH-1:0] read_data_a, read_data_b;
    logic write_enable = 0;
    logic [ADDR_WIDTH-1:0] write_addr = 0;
    logic [DATA_WIDTH-1:0] write_data = 0;
    integer tests = 0, errors = 0;

    register_file #(.DATA_WIDTH(DATA_WIDTH), .ADDR_WIDTH(ADDR_WIDTH)) dut (
        .clk(clk), .rst(rst),
        .read_addr_a(read_addr_a), .read_data_a(read_data_a),
        .read_addr_b(read_addr_b), .read_data_b(read_data_b),
        .write_enable(write_enable), .write_addr(write_addr), .write_data(write_data)
    );
    always #5 clk = ~clk;

    task automatic check(input logic [63:0] expected_a, expected_b, input string description);
        begin
            #1;
            tests = tests + 1;
            if (read_data_a !== expected_a || read_data_b !== expected_b) begin
                errors = errors + 1;
                $display("FAIL %0d %s: A=%h expected=%h B=%h expected=%h", tests, description,
                         read_data_a, expected_a, read_data_b, expected_b);
            end else $display("PASS %0d %s", tests, description);
        end
    endtask

    task automatic write_reg(input logic [7:0] address, input logic [63:0] value);
        begin
            @(negedge clk);
            write_enable = 1;
            write_addr = address;
            write_data = value;
            @(posedge clk);
            #1;
            @(negedge clk);
            write_enable = 0;
        end
    endtask

    initial begin
        $dumpfile("register_file.vcd");
        $dumpvars(0, register_file_tb);
        // Assert reset after time zero so its edge is unambiguous.
        #1 rst = 1;
        read_addr_a = 8'd1;
        read_addr_b = 8'd255;
        check(0, 0, "asynchronous reset clears registers");
        @(negedge clk);
        rst = 0;

        write_reg(8'd1, 64'd10);
        write_reg(8'd2, 64'd20);
        write_reg(8'd255, 64'hDEADBEEFCAFEBABE);
        read_addr_a = 8'd1;
        read_addr_b = 8'd2;
        check(10, 20, "two independent asynchronous reads");
        read_addr_a = 8'd255;
        read_addr_b = 8'd1;
        check(64'hDEADBEEFCAFEBABE, 10, "highest register address");

        write_reg(8'd0, 64'hFFFFFFFFFFFFFFFF);
        read_addr_a = 8'd0;
        read_addr_b = 8'd255;
        check(0, 64'hDEADBEEFCAFEBABE, "R0 ignores writes");

        // Inputs change but storage must not change before a rising edge.
        @(negedge clk);
        write_enable = 1;
        write_addr = 8'd2;
        write_data = 64'd99;
        read_addr_a = 8'd2;
        read_addr_b = 8'd2;
        check(20, 20, "write is not visible before rising edge");
        @(posedge clk);
        check(99, 99, "write visible after rising edge");
        @(negedge clk);
        write_enable = 0;
        write_data = 64'd1234;
        @(posedge clk);
        check(99, 99, "write disabled preserves register");

        // Reset clears previously written registers without waiting for a clock.
        @(negedge clk);
        rst = 1;
        read_addr_a = 8'd1;
        read_addr_b = 8'd255;
        check(0, 0, "asynchronous reset after writes");
        rst = 0;
        $display("TESTS=%0d PASSED=%0d FAILED=%0d", tests, tests-errors, errors);
        if (errors != 0) $fatal(1, "REGISTER FILE TEST FAILED");
        $display("ALL REGISTER FILE TESTS PASSED");
        $finish;
    end
endmodule

sim/waveforms/register_file.vcd
$date
	Tue Sep 29 12:15:58 2026
$end
$version
	Icarus Verilog
$end
$timescale
	1ps
$end
$scope module register_file_tb $end
$var wire 64 ! read_data_b [63:0] $end
$var wire 64 " read_data_a [63:0] $end
$var parameter 32 # ADDR_WIDTH $end
$var parameter 32 $ DATA_WIDTH $end
$var reg 1 % clk $end
$var reg 8 & read_addr_a [7:0] $end
$var reg 8 ' read_addr_b [7:0] $end
$var reg 1 ( rst $end
$var reg 8 ) write_addr [7:0] $end
$var reg 64 * write_data [63:0] $end
$var reg 1 + write_enable $end
$var integer 32 , errors [31:0] $end
$var integer 32 - tests [31:0] $end
$scope module dut $end
$var wire 1 % clk $end
$var wire 8 . read_addr_a [7:0] $end
$var wire 8 / read_addr_b [7:0] $end
$var wire 1 ( rst $end
$var wire 8 0 write_addr [7:0] $end
$var wire 64 1 write_data [63:0] $end
$var wire 1 + write_enable $end
$var wire 64 2 read_data_b [63:0] $end
$var wire 64 3 read_data_a [63:0] $end
$var parameter 32 4 ADDR_WIDTH $end
$var parameter 32 5 DATA_WIDTH $end
$var parameter 32 6 REG_COUNT $end
$var integer 32 7 i [31:0] $end
$upscope $end
$scope task check $end
$upscope $end
$scope task write_reg $end
$upscope $end
$upscope $end
$enddefinitions $end
$comment Show the parameter values. $end
$dumpall
b100000000 6
b1000000 5
b1000 4
b1000000 $
b1000 #
$end
#0
$dumpvars
bx 7
b0 3
b0 2
b0 1
b0 0
b0 /
b0 .
b0 -
b0 ,
0+
b0 *
b0 )
0(
b0 '
b0 &
0%
b0 "
b0 !
$end
#1000
b0 !
b0 2
b0 "
b0 3
b100000000 7
b11111111 '
b11111111 /
b1 &
b1 .
1(
#2000
b1 -
#5000
b100000000 7
1%
#10000
0(
0%
#15000
1%
#20000
b1010 *
b1010 1
b1 )
b1 0
1+
0%
#25000
b1010 "
b1010 3
1%
#30000
0+
0%
#35000
1%
#40000
b10100 *
b10100 1
b10 )
b10 0
1+
0%
#45000
1%
#50000
0+
0%
#55000
1%
#60000
b1101111010101101101111101110111111001010111111101011101010111110 *
b1101111010101101101111101110111111001010111111101011101010111110 1
b11111111 )
b11111111 0
1+
0%
#65000
b1101111010101101101111101110111111001010111111101011101010111110 !
b1101111010101101101111101110111111001010111111101011101010111110 2
1%
#70000
b10100 !
b10100 2
b10 '
b10 /
0+
0%
#71000
b1010 !
b1010 2
b1101111010101101101111101110111111001010111111101011101010111110 "
b1101111010101101101111101110111111001010111111101011101010111110 3
b1 '
b1 /
b11111111 &
b11111111 .
b10 -
#72000
b11 -
#75000
1%
#80000
b1111111111111111111111111111111111111111111111111111111111111111 *
b1111111111111111111111111111111111111111111111111111111111111111 1
b0 )
b0 0
1+
0%
#85000
1%
#90000
b1101111010101101101111101110111111001010111111101011101010111110 !
b1101111010101101101111101110111111001010111111101011101010111110 2
b0 "
b0 3
b11111111 '
b11111111 /
b0 &
b0 .
0+
0%
#91000
b100 -
#95000
1%
#100000
b10100 !
b10100 2
b10100 "
b10100 3
b10 '
b10 /
b10 &
b10 .
b1100011 *
b1100011 1
b10 )
b10 0
1+
0%
#101000
b101 -
#105000
b1100011 "
b1100011 3
b1100011 !
b1100011 2
1%
#106000
b110 -
#110000
b10011010010 *
b10011010010 1
0+
0%
#115000
1%
#116000
b111 -
#120000
b0 !
b0 2
b0 "
b0 3
b100000000 7
b11111111 '
b11111111 /
b1 &
b1 .
1(
0%
#121000
0(
b1000 -
